Workbook

Sheet נתונים והנחות
B1: מקרא צבעים
B2: ערך להזנה
B3: נתון לעדכון / בקרה
B4: נתון ממקור אמיתי (לא הערכה)
B5: נתון מוערך/נגזר (עם מקור)
B6: תרחיש A — טכנולוגיה קיימת
B7: תרחיש B — יעיל, ללא תמריץ
B8: תרחיש C — יעיל, עם תמריץ
B9: 1. פרמטרים פיננסיים
B10: שיעור מס חברות | C10: % | D10: רשות המסים | F10: 0.23
B11: שיעור היוון (יזמי / פרטי) | C11: % | D11: סוכם עם דניאל | E11: 6% — הוחלט עם דניאל 2026-07-13 (לעומת 10% תעשייתי שנשקל קודם) | F11: 0.06
B12: מחיר חשמל ממוצע לתעשייה | C12: אג'/קוט"ש | D12: חברת החשמל | E12: ממוצע SMP 2024 — נתון כללי, ייתכן שיעודכן לממוצע משוקלל לפי שעות תעו"ז | F12: 14
B14: 1ב. מחירי דלקים ומקדמי המרה (עבור בסיס משאבות חום)
B15: מחיר סולר בתעשייה | C15: ₪/ליטר | D15: משרד האנרגיה 2024 [1] | E15: מחירים תיאורטיים של מוצרי דלק שאינם בפיקוח, לפני מע"מ ובלו | F15: 2.59368
B16: מחיר מזוט בתעשייה | C16: ₪/טון | D16: משרד האנרגיה 2024 [1] | E16: תוקן מהיחידה שהוזנה במקור (₪/ק"ג -> ₪/טון) — הערך המקורי לא עקבי עם טווח המחירים בדוח המקורי | F16: 2344.72
B17: יחס קלורי — סולר | C17: טון דלק/MWh | D17: אקסל של עמרי (MRV) [2] | F17: 0.085
B18: יחס קלורי — מזוט | C18: טון דלק/MWh | D18: אקסל של עמרי (MRV) [2] | F18: 0.088
B19: צפיפות סולר | C19: ק"ג/ליטר | D19: אקסל של עמרי (MRV) [2] | E19: להמרת טון סולר לליטר במידה ונבחר סולר כדלק בסיס | F19: 0.82
B21: 2. פרמטר תמריץ — מכפיל פחת (פחת מואץ)
B22: מכפיל שיעור הפחת ← פרמטר המדיניות המרכזי | C22: מכפיל | D22: פרמטר ניתן לשינוי | E22: 1.0 = ללא תמריץ | 2.0 = קפריסין (כפול, 5 שנים) | 5.0 = 2 שנים | F22: 2
B23: מכפיל 2.0 + פחת סטנדרטי 10% = שיעור מואץ 20%/שנה למשך 5 שנים. סה"כ ניכוי = 100% CapEx — היתרון הוא קדמות הניכוי (Time Value of Money).
B24: דוגמאות: 1.0 = 10%/שנה × 10 שנים (סטנדרטי) | 2.0 = 20%/שנה × 5 שנים | 3.33 = 33%/שנה × 3 שנים | 5.0 = 50%/שנה × 2 שנים (מודל קפריסין/אירלנד)
B26: 3. שיעורי פחת סטנדרטיים — תקנות מס הכנסה
B27: משאבות חום | C27: % לשנה | D27: תקנות פחת | E27: ציוד מכני | F27: 0.1
B28: צ'ילרים | C28: % לשנה | D28: תקנות פחת | E28: ציוד מכני | F28: 0.1
B29: מדחסי VSD | C29: % לשנה | D29: תקנות פחת | E29: ציוד מכני | F29: 0.1
B31: * שיעורי הפחת הם הנחות עבודה — יש לוודא מול יועץ מס לפני הגשה
B33: 4. הנחות לפי טכנולוגיה — כל הנתונים לעדכון בטבלה זו
B34: פרמטר | C34: יחידות | D34: מקור | E34: הערות | F34: משאבות חום (חימום מים) | G34: צ'ילרים | H34: מדחסי VSD
F35: vs. תנור מזוט/סולר | G35: vs. מערכת קירור קונבנציונלית | H35: vs. מדחס מהירות קבועה
B36: קיבולת מותקנת | C36: ראו הערה | D36: baseline-technology-data.md — נקודת קיבולת נבחרת | F36: 40 | G36: 500 | H36: 45
B37: שעות פעילות שנתיות | C37: שעות | D37: ראו הערה בעמודת הטכנולוגיה | E37: ממתין לייעוץ מהנדס EcoTraders (משאבות חום) | צ'ילרים: 3,000 שעות (מספר עבודה) | VSD: 6,400 שעות (אמצע 6,000-6,800) | F37: PENDING | G37: 3000 | H37: 6400
B38: COP — משאבת חום (יעיל) | C38: יחס | D38: Sprsun — עמוד מפרט מוצר [3] | E38: רלוונטי למשאבות חום בלבד | F38: 4.13
B39: יעילות בעירה — תנור בסיס | C39: % | D39: ASME PTC 4 [4] | E39: רלוונטי למשאבות חום בלבד | F39: 0.835
B40: סוג דלק בסיס | C40: טקסט | D40: הנחת עבודה — ניתן לשנות | E40: רלוונטי למשאבות חום בלבד — "מזוט" או "סולר" | F40: מזוט
B41: יעילות אנרגטית — בסיסי | C41: ראו הערה | D41: ראו הערה בעמודת הטכנולוגיה | E41: רלוונטי לצ'ילרים/VSD בלבד | G41: 0.6 | H41: 21.5
B42: יעילות אנרגטית — יעיל | C42: ראו הערה | D42: ראו הערה בעמודת הטכנולוגיה | E42: רלוונטי לצ'ילרים/VSD בלבד | G42: 0.48 | H42: 16.5
B43: חיסכון אנרגטי (מחושב) | C43: % מצריכה | D43: חישוב | E43: רלוונטי לצ'ילרים/VSD בלבד — נגזר משורות 41-42 | F43: - | G43: =IF(AND(ISNUMBER(G41),ISNUMBER(G42)),(G41-G42)/G41,"PENDING") | H43: =IF(AND(ISNUMBER(H41),ISNUMBER(H42)),(H41-H42)/H41,"PENDING")
B44: צריכת אנרגיה/דלק שנתית — בסיסי | C44: ראו הערה | D44: חישוב — קיבולת × שעות × יעילות/COP | E44: טון דלק (משאבות חום) | קוט"ש (צ'ילרים/VSD) | F44: =IF(AND(ISNUMBER(F36),ISNUMBER(F37),ISNUMBER(F39)),(F36*F37/1000/F39)*IF(F40="מזוט",'נתונים והנחות'!$F$18,'נתונים והנחות'!$F$17),"PENDING") | G44: =IF(AND(ISNUMBER(G36),ISNUMBER(G37),ISNUMBER(G41)),G36*G41*G37,"PENDING") | H44: =IF(AND(ISNUMBER(H36),ISNUMBER(H37)),H36*H37,"PENDING")
B45: צריכת חשמל שנתית — יעיל | C45: קוט"ש/שנה | D45: חישוב | E45: הצד היעיל תמיד חשמלי בכל הטכנולוגיות | F45: =IF(AND(ISNUMBER(F36),ISNUMBER(F37),ISNUMBER(F38)),F36*F37/F38,"PENDING") | G45: =IF(AND(ISNUMBER(G44),ISNUMBER(G43)),G44*(1-G43),"PENDING") | H45: =IF(AND(ISNUMBER(H44),ISNUMBER(H43)),H44*(1-H43),"PENDING")
B47: CapEx — ציוד קיים (בסיסי) | C47: ₪ | D47: ראו הערה בעמודת הטכנולוגיה | F47: PENDING | G47: 1781000 | H47: 255061
B48: CapEx — ציוד יעיל | C48: ₪ | D48: ראו הערה בעמודת הטכנולוגיה | F48: 165177 | G48: 2093000 | H48: 312450
B49: ΔCapEx = יעיל − בסיסי | C49: ₪ | D49: חישוב | F49: =IF(ISNUMBER(F48)*ISNUMBER(F47),F48-F47,"PENDING") | G49: =IF(ISNUMBER(G48)*ISNUMBER(G47),G48-G47,"PENDING") | H49: =IF(ISNUMBER(H48)*ISNUMBER(H47),H48-H47,"PENDING")
B50: אורך חיים — ציוד בסיסי | C50: שנים | D50: ממצאי הנדסה / הנחת עבודה | F50: 15 | G50: 15 | H50: 12
B51: אורך חיים — ציוד יעיל | C51: שנים | D51: ממצאי הנדסה / הנחת עבודה | F51: 10 | G51: 17 | H51: 12
B52: גורם שחיקת ביצועים | C52: %/שנה | D52: הנחת עבודה (0.5-1%/שנה טיפוסי לציוד מכני) | F52: 0.005 | G52: 0.005 | H52: 0.005
B53: OPEX אחר — בסיסי (תחזוקה, חלפים...) | C53: ₪/שנה | D53: נתוני רפי (טרם התקבל) | E53: ⚠ ממתין לנתוני רפי | F53: PENDING | G53: PENDING | H53: PENDING
B54: OPEX אחר — יעיל (תחזוקה, חלפים...) | C54: ₪/שנה | D54: נתוני רפי (טרם התקבל) | E54: ⚠ ממתין לנתוני רפי | F54: PENDING | G54: PENDING | H54: PENDING
B55: OPEX אנרגיה/דלק שנה 1 — בסיסי | C55: ₪/שנה | D55: חישוב | E55: חישוב | F55: =IF(ISNUMBER(F44),IF(F40="מזוט",F44*'נתונים והנחות'!$F$16,F44*1000/'נתונים והנחות'!$F$19*'נתונים והנחות'!$F$15),"PENDING") | G55: =IF(ISNUMBER(G44),G44*'נתונים והנחות'!$F$12/100,"PENDING") | H55: =IF(ISNUMBER(H44),H44*'נתונים והנחות'!$F$12/100,"PENDING")
B56: OPEX אנרגיה שנה 1 — יעיל | C56: ₪/שנה | D56: חישוב | E56: חישוב | F56: =IF(ISNUMBER(F45),F45*'נתונים והנחות'!$F$12/100,"PENDING") | G56: =IF(ISNUMBER(G45),G45*'נתונים והנחות'!$F$12/100,"PENDING") | H56: =IF(ISNUMBER(H45),H45*'נתונים והנחות'!$F$12/100,"PENDING")
B58: * OPEX אחר ממתין לנתוני רפי. שאר הנתונים מקורם ב-baseline-technology-data.md ומספרים בהערות/מקורות למטה.
B61: 5. מקורות ומתודולוגיה
B62: [1] | C62: משרד האנרגיה, מינהל הדלק והגז — "מחירים תיאורטיים של מוצרי דלק שאינם בפיקוח", שנת 2024. קובץ המקור: orl22024_4.xlsx. מחירי סולר/מזוט בתעשייה ממוצעים לשנת 2024, לפני מע"מ ובלו.
B63: [2] | C63: אקסל של עמרי — מקדמי MRV (Monitoring, Reporting & Verification) הרשמיים של ישראל: ערכים קלוריים לסולר/מזוט וצפיפות סולר.
B64: [3] | C64: Sprsun commercial heat pump product pages — COP 4.13 at 40kW (37-45kW model), COP 3.23-3.24 at 70kW (42-70kW model). Real capacity ceiling is 70kW, not the 150kW originally assumed in an earlier draft.
B65: [4] | C65: ASME PTC 4 (fuel-to-heat combustion efficiency, fire-tube/water-tube units without heat recovery, 80-88% typical range — 83.5% midpoint used).
B66: [5] | C66: ASHRAE 90.1 Table 6.8.1-3 (chiller code-minimum, 500 RT bracket) + DOE FEMP designated-efficient level — baseline 0.60 kW/ton, efficient 0.48 kW/ton.
B67: [6] | C67: capex_all_rounds_annotated.xlsx, sheet "עלות לטון קירור" — 96 real chiller line items from the 2017-2022 grant program rounds, 27 with usable capacity data. Median ₪4,186/ton used for efficient CapEx (recommended over the mean in the source sheet due to flagged outliers). Baseline (₪3,562/ton = ₪4,186 / 1.175) estimated via a 10-25% efficiency cost premium (DOE FEMP cost-effectiveness data + general market commentary, midpoint used) — a derived estimate, not a direct quote.
B68: [7] | C68: capex_all_rounds_annotated.xlsx, sheet "חישוב ממוצע" — grant program averages: heat pumps ₪165,177/unit (49 units), VSD ₪312,450/unit (5 units). Blended averages, not split by capacity or baseline/efficient — applied as the efficient-side CapEx.
B69: [8] | C69: US Air Compressor (usaircompressor.com) — real listed prices: 60 HP (45kW) fixed-speed $18,150-19,800, 200 HP (150kW) fixed-speed $65,999.99. VSD baseline CapEx (₪255,061) estimated by dividing the grant-average VSD CapEx by a 15-30% VSD-over-fixed-speed premium (midpoint 22.5%) — a derived estimate.
B70: [9] | C70: CAGI specific power ranges (ISO 1217 basis) — fixed-speed 20-23 kW/100cfm, VSD 15-18 kW/100cfm at 100 psi reference pressure. Midpoints used (21.5 / 16.5).
B72: מקרא רמת ביטחון: ירוק = נתון אמיתי ממקור ראשוני (לא הערכה) | כתום-אפרסק = נתון נגזר/מוערך עם מתודולוגיה מוסברת | צהוב = ממתין לנתונים (רפי / ייעוץ מהנדס). ראו projects/energy-program/baseline-technology-data.md לפירוט המקורות המלא כולל קישורים.

Sheet ניתוח
B1: מקרא צבעים
B2: ערך להזנה
B3: נתון לעדכון / בקרה
B4: נתון ממקור אמיתי (לא הערכה)
B5: נתון מוערך/נגזר (עם מקור)
B6: תרחיש A — טכנולוגיה קיימת
B7: תרחיש B — יעיל, ללא תמריץ
B8: ניתוח כלכלי — פחת מואץ לפי טכנולוגיה | השוואת שלושה תרחישים
B9: פרמטר מדיניות מרכזי
B10: 1. פרמטרים פיננסיים
B11: שיעור מס חברות | C11: % | D11: נתונים והנחות | F11: ='נתונים והנחות'!$F$10
B12: שיעור היוון | C12: % | D12: נתונים והנחות | F12: ='נתונים והנחות'!$F$11
B13: מחיר חשמל (₪/קוט"ש) | C13: ₪/קוט"ש | D13: נתונים והנחות | F13: ='נתונים והנחות'!$F$12/100
B15: 2. פרמטר תמריץ — מכפיל פחת
B16: מכפיל שיעור הפחת ← שנה ב'נתונים והנחות'!F22 | C16: מכפיל | D16: נתונים והנחות | F16: ='נתונים והנחות'!$F$22
B17: מכפיל × פחת סטנדרטי = שיעור מואץ | סה"כ ניכוי = 100% CapEx | תקופת פחת = 1 ÷ שיעור מואץ
B19: 3. ניתוחים לפי טכנולוגיה
B21: 3.1 משאבות חום (חימום מים)
B22: * החלפת תנור מזוט/סולר במשאבת חום | אורך חיים: 10 vs 15 שנה | כל הנתונים: גיליון 'נתונים והנחות' — סעיף 4
B23: ב. לוחות פחת (ציוד בסיסי vs. יעיל)
B24: פרמטר | C24: יחידות | D24: מקור | E24: הערות | F24: שנה 0 (השקעה) | G24: שנה 1 | H24: שנה 2 | I24: שנה 3 | J24: שנה 4 | K24: שנה 5 | L24: שנה 6 | M24: שנה 7 | N24: שנה 8 | O24: שנה 9 | P24: שנה 10 | Q24: שנה 11 | R24: שנה 12 | S24: שנה 13 | T24: שנה 14 | U24: שנה 15 | V24: שנה 16 | W24: שנה 17 | X24: שנה 18 | Y24: שנה 19 | Z24: שנה 20
B25: פחת סטנדרטי — תנור מזוט/סולר | C25: ₪ | D25: חישוב | E25: קו ישר | 10%/שנה | עד 10 שנים | CapEx בסיסי | F25: 0 | G25: =IF(ISNUMBER('נתונים והנחות'!$F$47),'נתונים והנחות'!$F$47*0.1,0) | H25: =IF(ISNUMBER('נתונים והנחות'!$F$47),'נתונים והנחות'!$F$47*0.1,0) | I25: =IF(ISNUMBER('נתונים והנחות'!$F$47),'נתונים והנחות'!$F$47*0.1,0) | J25: =IF(ISNUMBER('נתונים והנחות'!$F$47),'נתונים והנחות'!$F$47*0.1,0) | K25: =IF(ISNUMBER('נתונים והנחות'!$F$47),'נתונים והנחות'!$F$47*0.1,0) | L25: =IF(ISNUMBER('נתונים והנחות'!$F$47),'נתונים והנחות'!$F$47*0.1,0) | M25: =IF(ISNUMBER('נתונים והנחות'!$F$47),'נתונים והנחות'!$F$47*0.1,0) | N25: =IF(ISNUMBER('נתונים והנחות'!$F$47),'נתונים והנחות'!$F$47*0.1,0) | ... P25: =IF(ISNUMBER('נתונים והנחות'!$F$47),'נתונים והנחות'!$F$47*0.1,0) | Q25: =0 | R25: =0 | S25: =0 | T25: =0 | U25: =0 | V25: =0 | W25: =0 | X25: =0 | ... Z25: =0
B26: מגן מס — תנור מזוט/סולר | C26: ₪ | D26: חישוב | E26: =פחת × שיעור מס | F26: 0 | G26: =G25*'נתונים והנחות'!$F$10 | H26: =H25*'נתונים והנחות'!$F$10 | I26: =I25*'נתונים והנחות'!$F$10 | J26: =J25*'נתונים והנחות'!$F$10 | K26: =K25*'נתונים והנחות'!$F$10 | L26: =L25*'נתונים והנחות'!$F$10 | M26: =M25*'נתונים והנחות'!$F$10 | N26: =N25*'נתונים והנחות'!$F$10 | ... Z26: =Z25*'נתונים והנחות'!$F$10
B27: פחת סטנדרטי — משאבות חום (חימום מים) | C27: ₪ | D27: חישוב | E27: קו ישר | 10%/שנה | עד 10 שנים | CapEx יעיל | F27: 0 | G27: =IF(ISNUMBER('נתונים והנחות'!$F$48),'נתונים והנחות'!$F$48*0.1,0) | H27: =IF(ISNUMBER('נתונים והנחות'!$F$48),'נתונים והנחות'!$F$48*0.1,0) | I27: =IF(ISNUMBER('נתונים והנחות'!$F$48),'נתונים והנחות'!$F$48*0.1,0) | J27: =IF(ISNUMBER('נתונים והנחות'!$F$48),'נתונים והנחות'!$F$48*0.1,0) | K27: =IF(ISNUMBER('נתונים והנחות'!$F$48),'נתונים והנחות'!$F$48*0.1,0) | L27: =IF(ISNUMBER('נתונים והנחות'!$F$48),'נתונים והנחות'!$F$48*0.1,0) | M27: =IF(ISNUMBER('נתונים והנחות'!$F$48),'נתונים והנחות'!$F$48*0.1,0) | N27: =IF(ISNUMBER('נתונים והנחות'!$F$48),'נתונים והנחות'!$F$48*0.1,0) | ... P27: =IF(ISNUMBER('נתונים והנחות'!$F$48),'נתונים והנחות'!$F$48*0.1,0) | Q27: =0 | R27: =0 | S27: =0 | T27: =0 | U27: =0 | V27: =0 | W27: =0 | X27: =0 | ... Z27: =0
B28: מגן מס סטנדרטי — משאבות חום (חימום מים) | C28: ₪ | D28: חישוב | E28: =פחת × שיעור מס | F28: 0 | G28: =G27*'נתונים והנחות'!$F$10 | H28: =H27*'נתונים והנחות'!$F$10 | I28: =I27*'נתונים והנחות'!$F$10 | J28: =J27*'נתונים והנחות'!$F$10 | K28: =K27*'נתונים והנחות'!$F$10 | L28: =L27*'נתונים והנחות'!$F$10 | M28: =M27*'נתונים והנחות'!$F$10 | N28: =N27*'נתונים והנחות'!$F$10 | ... Z28: =Z27*'נתונים והנחות'!$F$10
B29: פחת מואץ — משאבות חום (חימום מים) | C29: ₪ | D29: חישוב | E29: =CapEx יעיל × (פחת סטנדרטי × מכפיל) | תקופה = 1 ÷ שיעור מואץ | F29: 0 | G29: =IF(ISNUMBER('נתונים והנחות'!$F$48),IF(1<=ROUND(1/(0.1*'נתונים והנחות'!$F$22),0),'נתונים והנחות'!$F$48*0.1*'נתונים והנחות'!$F$22,0),0) | H29: =IF(ISNUMBER('נתונים והנחות'!$F$48),IF(2<=ROUND(1/(0.1*'נתונים והנחות'!$F$22),0),'נתונים והנחות'!$F$48*0.1*'נתונים והנחות'!$F$22,0),0) | I29: =IF(ISNUMBER('נתונים והנחות'!$F$48),IF(3<=ROUND(1/(0.1*'נתונים והנחות'!$F$22),0),'נתונים והנחות'!$F$48*0.1*'נתונים והנחות'!$F$22,0),0) | J29: =IF(ISNUMBER('נתונים והנחות'!$F$48),IF(4<=ROUND(1/(0.1*'נתונים והנחות'!$F$22),0),'נתונים והנחות'!$F$48*0.1*'נתונים והנחות'!$F$22,0),0) | K29: =IF(ISNUMBER('נתונים והנחות'!$F$48),IF(5<=ROUND(1/(0.1*'נתונים והנחות'!$F$22),0),'נתונים והנחות'!$F$48*0.1*'נתונים והנחות'!$F$22,0),0) | L29: =IF(ISNUMBER('נתונים והנחות'!$F$48),IF(6<=ROUND(1/(0.1*'נתונים והנחות'!$F$22),0),'נתונים והנחות'!$F$48*0.1*'נתונים והנחות'!$F$22,0),0) | M29: =IF(ISNUMBER('נתונים והנחות'!$F$48),IF(7<=ROUND(1/(0.1*'נתונים והנחות'!$F$22),0),'נתונים והנחות'!$F$48*0.1*'נתונים והנחות'!$F$22,0),0) | N29: =IF(ISNUMBER('נתונים והנחות'!$F$48),IF(8<=ROUND(1/(0.1*'נתונים והנחות'!$F$22),0),'נתונים והנחות'!$F$48*0.1*'נתונים והנחות'!$F$22,0),0) | O29: =IF(ISNUMBER('נתונים והנחות'!$F$48),IF(9<=ROUND(1/(0.1*'נתונים והנחות'!$F$22),0),'נתונים והנחות'!$F$48*0.1*'נתונים והנחות'!$F$22,0),0) | P29: =IF(ISNUMBER('נתונים והנחות'!$F$48),IF(10<=ROUND(1/(0.1*'נתונים והנחות'!$F$22),0),'נתונים והנחות'!$F$48*0.1*'נתונים והנחות'!$F$22,0),0) | Q29: =IF(ISNUMBER('נתונים והנחות'!$F$48),IF(11<=ROUND(1/(0.1*'נתונים והנחות'!$F$22),0),'נתונים והנחות'!$F$48*0.1*'נתונים והנחות'!$F$22,0),0) | R29: =IF(ISNUMBER('נתונים והנחות'!$F$48),IF(12<=ROUND(1/(0.1*'נתונים והנחות'!$F$22),0),'נתונים והנחות'!$F$48*0.1*'נתונים והנחות'!$F$22,0),0) | S29: =IF(ISNUMBER('נתונים והנחות'!$F$48),IF(13<=ROUND(1/(0.1*'נתונים והנחות'!$F$22),0),'נתונים והנחות'!$F$48*0.1*'נתונים והנחות'!$F$22,0),0) | T29: =IF(ISNUMBER('נתונים והנחות'!$F$48),IF(14<=ROUND(1/(0.1*'נתונים והנחות'!$F$22),0),'נתונים והנחות'!$F$48*0.1*'נתונים והנחות'!$F$22,0),0) | U29: =IF(ISNUMBER('נתונים והנחות'!$F$48),IF(15<=ROUND(1/(0.1*'נתונים והנחות'!$F$22),0),'נתונים והנחות'!$F$48*0.1*'נתונים והנחות'!$F$22,0),0) | V29: =IF(ISNUMBER('נתונים והנחות'!$F$48),IF(16<=ROUND(1/(0.1*'נתונים והנחות'!$F$22),0),'נתונים והנחות'!$F$48*0.1*'נתונים והנחות'!$F$22,0),0) | W29: =IF(ISNUMBER('נתונים והנחות'!$F$48),IF(17<=ROUND(1/(0.1*'נתונים והנחות'!$F$22),0),'נתונים והנחות'!$F$48*0.1*'נתונים והנחות'!$F$22,0),0) | X29: =IF(ISNUMBER('נתונים והנחות'!$F$48),IF(18<=ROUND(1/(0.1*'נתונים והנחות'!$F$22),0),'נתונים והנחות'!$F$48*0.1*'נתונים והנחות'!$F$22,0),0) | Y29: =IF(ISNUMBER('נתונים והנחות'!$F$48),IF(19<=ROUND(1/(0.1*'נתונים והנחות'!$F$22),0),'נתונים והנחות'!$F$48*0.1*'נתונים והנחות'!$F$22,0),0) | Z29: =IF(ISNUMBER('נתונים והנחות'!$F$48),IF(20<=ROUND(1/(0.1*'נתונים והנחות'!$F$22),0),'נתונים והנחות'!$F$48*0.1*'נתונים והנחות'!$F$22,0),0)
B30: מגן מס מואץ — משאבות חום (חימום מים) | C30: ₪ | D30: חישוב | E30: =פחת מואץ × שיעור מס | F30: 0 | G30: =G29*'נתונים והנחות'!$F$10 | H30: =H29*'נתונים והנחות'!$F$10 | I30: =I29*'נתונים והנחות'!$F$10 | J30: =J29*'נתונים והנחות'!$F$10 | K30: =K29*'נתונים והנחות'!$F$10 | L30: =L29*'נתונים והנחות'!$F$10 | M30: =M29*'נתונים והנחות'!$F$10 | N30: =N29*'נתונים והנחות'!$F$10 | ... Z30: =Z29*'נתונים והנחות'!$F$10
B32: ג. ניתוח תזרים מזומנים — שלושה תרחישים
B33: פרמטר | C33: יחידות | D33: מקור | E33: הערות | F33: שנה 0 (השקעה) | G33: שנה 1 | H33: שנה 2 | I33: שנה 3 | J33: שנה 4 | K33: שנה 5 | L33: שנה 6 | M33: שנה 7 | N33: שנה 8 | O33: שנה 9 | P33: שנה 10 | Q33: שנה 11 | R33: שנה 12 | S33: שנה 13 | T33: שנה 14 | U33: שנה 15 | V33: שנה 16 | W33: שנה 17 | X33: שנה 18 | Y33: שנה 19 | Z33: שנה 20
B34: תרחיש A — רכישת תנור מזוט/סולר (ציוד קיים / לא יעיל)
B35: השקעה ראשונית | C35: ₪ | D35: חישוב | F35: =IF(ISNUMBER('נתונים והנחות'!$F$47),-'נתונים והנחות'!$F$47,"PENDING")
B36: OPEX אנרגיה | C36: ₪ | D36: חישוב | F36: 0 | G36: =IF(ISNUMBER('נתונים והנחות'!$F$55),-'נתונים והנחות'!$F$55,0) | H36: =IF(ISNUMBER('נתונים והנחות'!$F$55),-'נתונים והנחות'!$F$55,0) | I36: =IF(ISNUMBER('נתונים והנחות'!$F$55),-'נתונים והנחות'!$F$55,0) | J36: =IF(ISNUMBER('נתונים והנחות'!$F$55),-'נתונים והנחות'!$F$55,0) | K36: =IF(ISNUMBER('נתונים והנחות'!$F$55),-'נתונים והנחות'!$F$55,0) | L36: =IF(ISNUMBER('נתונים והנחות'!$F$55),-'נתונים והנחות'!$F$55,0) | M36: =IF(ISNUMBER('נתונים והנחות'!$F$55),-'נתונים והנחות'!$F$55,0) | N36: =IF(ISNUMBER('נתונים והנחות'!$F$55),-'נתונים והנחות'!$F$55,0) | ... U36: =IF(ISNUMBER('נתונים והנחות'!$F$55),-'נתונים והנחות'!$F$55,0) | V36: =0 | W36: =0 | X36: =0 | Y36: =0 | Z36: =0
B37: OPEX אחר (תחזוקה וכו') | C37: ₪ | D37: חישוב | F37: 0 | G37: =IF(ISNUMBER('נתונים והנחות'!$F$53),-'נתונים והנחות'!$F$53,0) | H37: =IF(ISNUMBER('נתונים והנחות'!$F$53),-'נתונים והנחות'!$F$53,0) | I37: =IF(ISNUMBER('נתונים והנחות'!$F$53),-'נתונים והנחות'!$F$53,0) | J37: =IF(ISNUMBER('נתונים והנחות'!$F$53),-'נתונים והנחות'!$F$53,0) | K37: =IF(ISNUMBER('נתונים והנחות'!$F$53),-'נתונים והנחות'!$F$53,0) | L37: =IF(ISNUMBER('נתונים והנחות'!$F$53),-'נתונים והנחות'!$F$53,0) | M37: =IF(ISNUMBER('נתונים והנחות'!$F$53),-'נתונים והנחות'!$F$53,0) | N37: =IF(ISNUMBER('נתונים והנחות'!$F$53),-'נתונים והנחות'!$F$53,0) | ... U37: =IF(ISNUMBER('נתונים והנחות'!$F$53),-'נתונים והנחות'!$F$53,0) | V37: =0 | W37: =0 | X37: =0 | Y37: =0 | Z37: =0
B38: תזרים נקי — תרחיש A | C38: ₪ | D38: חישוב | F38: =F35 | G38: =G36+G37+G26 | H38: =H36+H37+H26 | I38: =I36+I37+I26 | J38: =J36+J37+J26 | K38: =K36+K37+K26 | L38: =L36+L37+L26 | M38: =M36+M37+M26 | N38: =N36+N37+N26 | ... Z38: =Z36+Z37+Z26
B39: תזרים מהוון — תרחיש A | C39: ₪ | D39: חישוב | F39: =F38 | G39: =G38/(1+'נתונים והנחות'!$F$11)^1 | H39: =H38/(1+'נתונים והנחות'!$F$11)^2 | I39: =I38/(1+'נתונים והנחות'!$F$11)^3 | J39: =J38/(1+'נתונים והנחות'!$F$11)^4 | K39: =K38/(1+'נתונים והנחות'!$F$11)^5 | L39: =L38/(1+'נתונים והנחות'!$F$11)^6 | M39: =M38/(1+'נתונים והנחות'!$F$11)^7 | N39: =N38/(1+'נתונים והנחות'!$F$11)^8 | O39: =O38/(1+'נתונים והנחות'!$F$11)^9 | P39: =P38/(1+'נתונים והנחות'!$F$11)^10 | Q39: =Q38/(1+'נתונים והנחות'!$F$11)^11 | R39: =R38/(1+'נתונים והנחות'!$F$11)^12 | S39: =S38/(1+'נתונים והנחות'!$F$11)^13 | T39: =T38/(1+'נתונים והנחות'!$F$11)^14 | U39: =U38/(1+'נתונים והנחות'!$F$11)^15 | V39: =V38/(1+'נתונים והנחות'!$F$11)^16 | W39: =W38/(1+'נתונים והנחות'!$F$11)^17 | X39: =X38/(1+'נתונים והנחות'!$F$11)^18 | Y39: =Y38/(1+'נתונים והנחות'!$F$11)^19 | Z39: =Z38/(1+'נתונים והנחות'!$F$11)^20
B40: NPV מצטבר — תרחיש A | C40: ₪ | D40: חישוב | F40: =F39 | G40: =F40+G39 | H40: =G40+H39 | I40: =H40+I39 | J40: =I40+J39 | K40: =J40+K39 | L40: =K40+L39 | M40: =L40+M39 | N40: =M40+N39 | ... Z40: =Y40+Z39
B42: תרחיש B — רכישת משאבות חום (חימום מים) | פחת סטנדרטי (ללא תמריץ)
B43: השקעה ראשונית | C43: ₪ | D43: חישוב | F43: =IF(ISNUMBER('נתונים והנחות'!$F$48),-'נתונים והנחות'!$F$48,"PENDING")
B44: OPEX אנרגיה (עם שחיקה שנתית) | C44: ₪ | D44: חישוב | F44: 0 | G44: =IF(ISNUMBER('נתונים והנחות'!$F$56),-'נתונים והנחות'!$F$56*(1-'נתונים והנחות'!$F$52)^0,0) | H44: =IF(ISNUMBER('נתונים והנחות'!$F$56),-'נתונים והנחות'!$F$56*(1-'נתונים והנחות'!$F$52)^1,0) | I44: =IF(ISNUMBER('נתונים והנחות'!$F$56),-'נתונים והנחות'!$F$56*(1-'נתונים והנחות'!$F$52)^2,0) | J44: =IF(ISNUMBER('נתונים והנחות'!$F$56),-'נתונים והנחות'!$F$56*(1-'נתונים והנחות'!$F$52)^3,0) | K44: =IF(ISNUMBER('נתונים והנחות'!$F$56),-'נתונים והנחות'!$F$56*(1-'נתונים והנחות'!$F$52)^4,0) | L44: =IF(ISNUMBER('נתונים והנחות'!$F$56),-'נתונים והנחות'!$F$56*(1-'נתונים והנחות'!$F$52)^5,0) | M44: =IF(ISNUMBER('נתונים והנחות'!$F$56),-'נתונים והנחות'!$F$56*(1-'נתונים והנחות'!$F$52)^6,0) | N44: =IF(ISNUMBER('נתונים והנחות'!$F$56),-'נתונים והנחות'!$F$56*(1-'נתונים והנחות'!$F$52)^7,0) | O44: =IF(ISNUMBER('נתונים והנחות'!$F$56),-'נתונים והנחות'!$F$56*(1-'נתונים והנחות'!$F$52)^8,0) | P44: =IF(ISNUMBER('נתונים והנחות'!$F$56),-'נתונים והנחות'!$F$56*(1-'נתונים והנחות'!$F$52)^9,0) | Q44: =0 | R44: =0 | S44: =0 | T44: =0 | U44: =0 | V44: =0 | W44: =0 | X44: =0 | ... Z44: =0
B45: OPEX אחר (תחזוקה וכו') | C45: ₪ | D45: חישוב | F45: 0 | G45: =IF(ISNUMBER('נתונים והנחות'!$F$54),-'נתונים והנחות'!$F$54,0) | H45: =IF(ISNUMBER('נתונים והנחות'!$F$54),-'נתונים והנחות'!$F$54,0) | I45: =IF(ISNUMBER('נתונים והנחות'!$F$54),-'נתונים והנחות'!$F$54,0) | J45: =IF(ISNUMBER('נתונים והנחות'!$F$54),-'נתונים והנחות'!$F$54,0) | K45: =IF(ISNUMBER('נתונים והנחות'!$F$54),-'נתונים והנחות'!$F$54,0) | L45: =IF(ISNUMBER('נתונים והנחות'!$F$54),-'נתונים והנחות'!$F$54,0) | M45: =IF(ISNUMBER('נתונים והנחות'!$F$54),-'נתונים והנחות'!$F$54,0) | N45: =IF(ISNUMBER('נתונים והנחות'!$F$54),-'נתונים והנחות'!$F$54,0) | ... P45: =IF(ISNUMBER('נתונים והנחות'!$F$54),-'נתונים והנחות'!$F$54,0) | Q45: =0 | R45: =0 | S45: =0 | T45: =0 | U45: =0 | V45: =0 | W45: =0 | X45: =0 | ... Z45: =0
B46: תזרים נקי — תרחיש B | C46: ₪ | D46: חישוב | F46: =F43 | G46: =G44+G45+G28 | H46: =H44+H45+H28 | I46: =I44+I45+I28 | J46: =J44+J45+J28 | K46: =K44+K45+K28 | L46: =L44+L45+L28 | M46: =M44+M45+M28 | N46: =N44+N45+N28 | ... Z46: =Z44+Z45+Z28
B47: תזרים מהוון — תרחיש B | C47: ₪ | D47: חישוב | F47: =F46 | G47: =G46/(1+'נתונים והנחות'!$F$11)^1 | H47: =H46/(1+'נתונים והנחות'!$F$11)^2 | I47: =I46/(1+'נתונים והנחות'!$F$11)^3 | J47: =J46/(1+'נתונים והנחות'!$F$11)^4 | K47: =K46/(1+'נתונים והנחות'!$F$11)^5 | L47: =L46/(1+'נתונים והנחות'!$F$11)^6 | M47: =M46/(1+'נתונים והנחות'!$F$11)^7 | N47: =N46/(1+'נתונים והנחות'!$F$11)^8 | O47: =O46/(1+'נתונים והנחות'!$F$11)^9 | P47: =P46/(1+'נתונים והנחות'!$F$11)^10 | Q47: =Q46/(1+'נתונים והנחות'!$F$11)^11 | R47: =R46/(1+'נתונים והנחות'!$F$11)^12 | S47: =S46/(1+'נתונים והנחות'!$F$11)^13 | T47: =T46/(1+'נתונים והנחות'!$F$11)^14 | U47: =U46/(1+'נתונים והנחות'!$F$11)^15 | V47: =V46/(1+'נתונים והנחות'!$F$11)^16 | W47: =W46/(1+'נתונים והנחות'!$F$11)^17 | X47: =X46/(1+'נתונים והנחות'!$F$11)^18 | Y47: =Y46/(1+'נתונים והנחות'!$F$11)^19 | Z47: =Z46/(1+'נתונים והנחות'!$F$11)^20
B48: NPV מצטבר — תרחיש B | C48: ₪ | D48: חישוב | F48: =F47 | G48: =F48+G47 | H48: =G48+H47 | I48: =H48+I47 | J48: =I48+J47 | K48: =J48+K47 | L48: =K48+L47 | M48: =L48+M47 | N48: =M48+N47 | ... Z48: =Y48+Z47
B50: תרחיש C — רכישת משאבות חום (חימום מים) | פחת מואץ (עם תמריץ)
B51: * OPEX זהה לתרחיש B — ההבדל הוא מגן המס המואץ בלבד
B52: תזרים נקי — תרחיש C | C52: ₪ | D52: חישוב | F52: =F43 | G52: =G44+G45+G30 | H52: =H44+H45+H30 | I52: =I44+I45+I30 | J52: =J44+J45+J30 | K52: =K44+K45+K30 | L52: =L44+L45+L30 | M52: =M44+M45+M30 | N52: =N44+N45+N30 | ... Z52: =Z44+Z45+Z30
B53: תזרים מהוון — תרחיש C | C53: ₪ | D53: חישוב | F53: =F52 | G53: =G52/(1+'נתונים והנחות'!$F$11)^1 | H53: =H52/(1+'נתונים והנחות'!$F$11)^2 | I53: =I52/(1+'נתונים והנחות'!$F$11)^3 | J53: =J52/(1+'נתונים והנחות'!$F$11)^4 | K53: =K52/(1+'נתונים והנחות'!$F$11)^5 | L53: =L52/(1+'נתונים והנחות'!$F$11)^6 | M53: =M52/(1+'נתונים והנחות'!$F$11)^7 | N53: =N52/(1+'נתונים והנחות'!$F$11)^8 | O53: =O52/(1+'נתונים והנחות'!$F$11)^9 | P53: =P52/(1+'נתונים והנחות'!$F$11)^10 | Q53: =Q52/(1+'נתונים והנחות'!$F$11)^11 | R53: =R52/(1+'נתונים והנחות'!$F$11)^12 | S53: =S52/(1+'נתונים והנחות'!$F$11)^13 | T53: =T52/(1+'נתונים והנחות'!$F$11)^14 | U53: =U52/(1+'נתונים והנחות'!$F$11)^15 | V53: =V52/(1+'נתונים והנחות'!$F$11)^16 | W53: =W52/(1+'נתונים והנחות'!$F$11)^17 | X53: =X52/(1+'נתונים והנחות'!$F$11)^18 | Y53: =Y52/(1+'נתונים והנחות'!$F$11)^19 | Z53: =Z52/(1+'נתונים והנחות'!$F$11)^20
B54: NPV מצטבר — תרחיש C | C54: ₪ | D54: חישוב | F54: =F53 | G54: =F54+G53 | H54: =G54+H53 | I54: =H54+I53 | J54: =I54+J53 | K54: =J54+K53 | L54: =K54+L53 | M54: =L54+M53 | N54: =M54+N53 | ... Z54: =Y54+Z53
B56: ד. תוצאות
B57: NPV — תרחיש A (תנור מזוט/סולר) | C57: ש"ח | F57: =SUM(F39:Z39)
B58: NPV — תרחיש B (משאבות חום (חימום מים), ללא תמריץ) | C58: ש"ח | F58: =SUM(F47:Z47)
B59: NPV — תרחיש C (משאבות חום (חימום מים), עם תמריץ) | C59: ש"ח | F59: =SUM(F53:Z53)
B61: NPV מצטבר — הצדקת השדרוג (B−A) | C61: ש"ח | F61: =F58-F57
B62: ערך התמריץ — תועלת הפחת המואץ (C−B) | C62: ש"ח | F62: =F59-F58
B64: ROI — תרחיש A | C64: % | F64: =IF(ISNUMBER('נתונים והנחות'!$F$47),(SUM(F39:Z39)+'נתונים והנחות'!$F$47)/'נתונים והנחות'!$F$47,"PENDING")
B65: ROI — תרחיש B | C65: % | F65: =IF(ISNUMBER('נתונים והנחות'!$F$48),(SUM(F47:Z47)+'נתונים והנחות'!$F$48)/'נתונים והנחות'!$F$48,"PENDING")
B66: ROI — תרחיש C | C66: % | F66: =IF(ISNUMBER('נתונים והנחות'!$F$48),(SUM(F53:Z53)+'נתונים והנחות'!$F$48)/'נתונים והנחות'!$F$48,"PENDING")
B68: תקופת החזר ΔCapEx ללא תמריץ (B−A) | C68: שנים | E68: זמן להחזר ההשקעה הנוספת | מחושב על ΔCF = CF_B − CF_A | F68: =IFERROR(MATCH(1,(F74:Z74>0)*1,0)-2+ABS(INDEX(F74:Z74,MATCH(1,(F74:Z74>0)*1,0)-1))/(INDEX(F74:Z74,MATCH(1,(F74:Z74>0)*1,0))-INDEX(F74:Z74,MATCH(1,(F74:Z74>0)*1,0)-1)),"לא מגיע לפירעון")
B69: תקופת החזר ΔCapEx עם תמריץ (C−A) | C69: שנים | E69: כולל יתרון מגן המס המואץ | מחושב על ΔCF = CF_C − CF_A | F69: =IFERROR(MATCH(1,(F75:Z75>0)*1,0)-2+ABS(INDEX(F75:Z75,MATCH(1,(F75:Z75>0)*1,0)-1))/(INDEX(F75:Z75,MATCH(1,(F75:Z75>0)*1,0))-INDEX(F75:Z75,MATCH(1,(F75:Z75>0)*1,0)-1)),"לא מגיע לפירעון")
B72: NPV מצטבר — מנקודת מבט ΔCapEx (לחישוב תקופת החזר על השקעה נוספת)
B73: פרמטר | C73: יחידות | D73: מקור | E73: הערות | F73: שנה 0 | G73: שנה 1 | H73: שנה 2 | I73: שנה 3 | J73: שנה 4 | K73: שנה 5 | L73: שנה 6 | M73: שנה 7 | N73: שנה 8 | O73: שנה 9 | P73: שנה 10 | Q73: שנה 11 | R73: שנה 12 | S73: שנה 13 | T73: שנה 14 | U73: שנה 15 | V73: שנה 16 | W73: שנה 17 | X73: שנה 18 | Y73: שנה 19 | Z73: שנה 20
B74: NPV מצטבר ΔCF — שדרוג ללא תמריץ (B−A) | C74: ₪ | D74: חישוב | F74: =IF(ISNUMBER('נתונים והנחות'!$F$49),-'נתונים והנחות'!$F$49,"PENDING") | G74: =F74+(G47-G39) | H74: =G74+(H47-H39) | I74: =H74+(I47-I39) | J74: =I74+(J47-J39) | K74: =J74+(K47-K39) | L74: =K74+(L47-L39) | M74: =L74+(M47-M39) | N74: =M74+(N47-N39) | ... Z74: =Y74+(Z47-Z39)
B75: NPV מצטבר ΔCF — שדרוג עם תמריץ (C−A) | C75: ₪ | D75: חישוב | F75: =IF(ISNUMBER('נתונים והנחות'!$F$49),-'נתונים והנחות'!$F$49,"PENDING") | G75: =F75+(G53-G39) | H75: =G75+(H53-H39) | I75: =H75+(I53-I39) | J75: =I75+(J53-J39) | K75: =J75+(K53-K39) | L75: =K75+(L53-L39) | M75: =L75+(M53-M39) | N75: =M75+(N53-N39) | ... Z75: =Y75+(Z53-Z39)
B79: 3.2 צ'ילרים
B80: * שדרוג מערכת קירור תעשייתית | אורך חיים: 17 vs 15 שנה | כל הנתונים: גיליון 'נתונים והנחות' — סעיף 4
B81: ב. לוחות פחת (ציוד בסיסי vs. יעיל)
B82: פרמטר | C82: יחידות | D82: מקור | E82: הערות | F82: שנה 0 (השקעה) | G82: שנה 1 | H82: שנה 2 | I82: שנה 3 | J82: שנה 4 | K82: שנה 5 | L82: שנה 6 | M82: שנה 7 | N82: שנה 8 | O82: שנה 9 | P82: שנה 10 | Q82: שנה 11 | R82: שנה 12 | S82: שנה 13 | T82: שנה 14 | U82: שנה 15 | V82: שנה 16 | W82: שנה 17 | X82: שנה 18 | Y82: שנה 19 | Z82: שנה 20
B83: פחת סטנדרטי — מערכת קירור קונבנציונלית | C83: ₪ | D83: חישוב | E83: קו ישר | 10%/שנה | עד 10 שנים | CapEx בסיסי | F83: 0 | G83: =IF(ISNUMBER('נתונים והנחות'!$G$47),'נתונים והנחות'!$G$47*0.1,0) | H83: =IF(ISNUMBER('נתונים והנחות'!$G$47),'נתונים והנחות'!$G$47*0.1,0) | I83: =IF(ISNUMBER('נתונים והנחות'!$G$47),'נתונים והנחות'!$G$47*0.1,0) | J83: =IF(ISNUMBER('נתונים והנחות'!$G$47),'נתונים והנחות'!$G$47*0.1,0) | K83: =IF(ISNUMBER('נתונים והנחות'!$G$47),'נתונים והנחות'!$G$47*0.1,0) | L83: =IF(ISNUMBER('נתונים והנחות'!$G$47),'נתונים והנחות'!$G$47*0.1,0) | M83: =IF(ISNUMBER('נתונים והנחות'!$G$47),'נתונים והנחות'!$G$47*0.1,0) | N83: =IF(ISNUMBER('נתונים והנחות'!$G$47),'נתונים והנחות'!$G$47*0.1,0) | ... P83: =IF(ISNUMBER('נתונים והנחות'!$G$47),'נתונים והנחות'!$G$47*0.1,0) | Q83: =0 | R83: =0 | S83: =0 | T83: =0 | U83: =0 | V83: =0 | W83: =0 | X83: =0 | ... Z83: =0
B84: מגן מס — מערכת קירור קונבנציונלית | C84: ₪ | D84: חישוב | E84: =פחת × שיעור מס | F84: 0 | G84: =G83*'נתונים והנחות'!$F$10 | H84: =H83*'נתונים והנחות'!$F$10 | I84: =I83*'נתונים והנחות'!$F$10 | J84: =J83*'נתונים והנחות'!$F$10 | K84: =K83*'נתונים והנחות'!$F$10 | L84: =L83*'נתונים והנחות'!$F$10 | M84: =M83*'נתונים והנחות'!$F$10 | N84: =N83*'נתונים והנחות'!$F$10 | ... Z84: =Z83*'נתונים והנחות'!$F$10
B85: פחת סטנדרטי — צ'ילרים | C85: ₪ | D85: חישוב | E85: קו ישר | 10%/שנה | עד 10 שנים | CapEx יעיל | F85: 0 | G85: =IF(ISNUMBER('נתונים והנחות'!$G$48),'נתונים והנחות'!$G$48*0.1,0) | H85: =IF(ISNUMBER('נתונים והנחות'!$G$48),'נתונים והנחות'!$G$48*0.1,0) | I85: =IF(ISNUMBER('נתונים והנחות'!$G$48),'נתונים והנחות'!$G$48*0.1,0) | J85: =IF(ISNUMBER('נתונים והנחות'!$G$48),'נתונים והנחות'!$G$48*0.1,0) | K85: =IF(ISNUMBER('נתונים והנחות'!$G$48),'נתונים והנחות'!$G$48*0.1,0) | L85: =IF(ISNUMBER('נתונים והנחות'!$G$48),'נתונים והנחות'!$G$48*0.1,0) | M85: =IF(ISNUMBER('נתונים והנחות'!$G$48),'נתונים והנחות'!$G$48*0.1,0) | N85: =IF(ISNUMBER('נתונים והנחות'!$G$48),'נתונים והנחות'!$G$48*0.1,0) | ... P85: =IF(ISNUMBER('נתונים והנחות'!$G$48),'נתונים והנחות'!$G$48*0.1,0) | Q85: =0 | R85: =0 | S85: =0 | T85: =0 | U85: =0 | V85: =0 | W85: =0 | X85: =0 | ... Z85: =0
B86: מגן מס סטנדרטי — צ'ילרים | C86: ₪ | D86: חישוב | E86: =פחת × שיעור מס | F86: 0 | G86: =G85*'נתונים והנחות'!$F$10 | H86: =H85*'נתונים והנחות'!$F$10 | I86: =I85*'נתונים והנחות'!$F$10 | J86: =J85*'נתונים והנחות'!$F$10 | K86: =K85*'נתונים והנחות'!$F$10 | L86: =L85*'נתונים והנחות'!$F$10 | M86: =M85*'נתונים והנחות'!$F$10 | N86: =N85*'נתונים והנחות'!$F$10 | ... Z86: =Z85*'נתונים והנחות'!$F$10
B87: פחת מואץ — צ'ילרים | C87: ₪ | D87: חישוב | E87: =CapEx יעיל × (פחת סטנדרטי × מכפיל) | תקופה = 1 ÷ שיעור מואץ | F87: 0 | G87: =IF(ISNUMBER('נתונים והנחות'!$G$48),IF(1<=ROUND(1/(0.1*'נתונים והנחות'!$F$22),0),'נתונים והנחות'!$G$48*0.1*'נתונים והנחות'!$F$22,0),0) | H87: =IF(ISNUMBER('נתונים והנחות'!$G$48),IF(2<=ROUND(1/(0.1*'נתונים והנחות'!$F$22),0),'נתונים והנחות'!$G$48*0.1*'נתונים והנחות'!$F$22,0),0) | I87: =IF(ISNUMBER('נתונים והנחות'!$G$48),IF(3<=ROUND(1/(0.1*'נתונים והנחות'!$F$22),0),'נתונים והנחות'!$G$48*0.1*'נתונים והנחות'!$F$22,0),0) | J87: =IF(ISNUMBER('נתונים והנחות'!$G$48),IF(4<=ROUND(1/(0.1*'נתונים והנחות'!$F$22),0),'נתונים והנחות'!$G$48*0.1*'נתונים והנחות'!$F$22,0),0) | K87: =IF(ISNUMBER('נתונים והנחות'!$G$48),IF(5<=ROUND(1/(0.1*'נתונים והנחות'!$F$22),0),'נתונים והנחות'!$G$48*0.1*'נתונים והנחות'!$F$22,0),0) | L87: =IF(ISNUMBER('נתונים והנחות'!$G$48),IF(6<=ROUND(1/(0.1*'נתונים והנחות'!$F$22),0),'נתונים והנחות'!$G$48*0.1*'נתונים והנחות'!$F$22,0),0) | M87: =IF(ISNUMBER('נתונים והנחות'!$G$48),IF(7<=ROUND(1/(0.1*'נתונים והנחות'!$F$22),0),'נתונים והנחות'!$G$48*0.1*'נתונים והנחות'!$F$22,0),0) | N87: =IF(ISNUMBER('נתונים והנחות'!$G$48),IF(8<=ROUND(1/(0.1*'נתונים והנחות'!$F$22),0),'נתונים והנחות'!$G$48*0.1*'נתונים והנחות'!$F$22,0),0) | O87: =IF(ISNUMBER('נתונים והנחות'!$G$48),IF(9<=ROUND(1/(0.1*'נתונים והנחות'!$F$22),0),'נתונים והנחות'!$G$48*0.1*'נתונים והנחות'!$F$22,0),0) | P87: =IF(ISNUMBER('נתונים והנחות'!$G$48),IF(10<=ROUND(1/(0.1*'נתונים והנחות'!$F$22),0),'נתונים והנחות'!$G$48*0.1*'נתונים והנחות'!$F$22,0),0) | Q87: =IF(ISNUMBER('נתונים והנחות'!$G$48),IF(11<=ROUND(1/(0.1*'נתונים והנחות'!$F$22),0),'נתונים והנחות'!$G$48*0.1*'נתונים והנחות'!$F$22,0),0) | R87: =IF(ISNUMBER('נתונים והנחות'!$G$48),IF(12<=ROUND(1/(0.1*'נתונים והנחות'!$F$22),0),'נתונים והנחות'!$G$48*0.1*'נתונים והנחות'!$F$22,0),0) | S87: =IF(ISNUMBER('נתונים והנחות'!$G$48),IF(13<=ROUND(1/(0.1*'נתונים והנחות'!$F$22),0),'נתונים והנחות'!$G$48*0.1*'נתונים והנחות'!$F$22,0),0) | T87: =IF(ISNUMBER('נתונים והנחות'!$G$48),IF(14<=ROUND(1/(0.1*'נתונים והנחות'!$F$22),0),'נתונים והנחות'!$G$48*0.1*'נתונים והנחות'!$F$22,0),0) | U87: =IF(ISNUMBER('נתונים והנחות'!$G$48),IF(15<=ROUND(1/(0.1*'נתונים והנחות'!$F$22),0),'נתונים והנחות'!$G$48*0.1*'נתונים והנחות'!$F$22,0),0) | V87: =IF(ISNUMBER('נתונים והנחות'!$G$48),IF(16<=ROUND(1/(0.1*'נתונים והנחות'!$F$22),0),'נתונים והנחות'!$G$48*0.1*'נתונים והנחות'!$F$22,0),0) | W87: =IF(ISNUMBER('נתונים והנחות'!$G$48),IF(17<=ROUND(1/(0.1*'נתונים והנחות'!$F$22),0),'נתונים והנחות'!$G$48*0.1*'נתונים והנחות'!$F$22,0),0) | X87: =IF(ISNUMBER('נתונים והנחות'!$G$48),IF(18<=ROUND(1/(0.1*'נתונים והנחות'!$F$22),0),'נתונים והנחות'!$G$48*0.1*'נתונים והנחות'!$F$22,0),0) | Y87: =IF(ISNUMBER('נתונים והנחות'!$G$48),IF(19<=ROUND(1/(0.1*'נתונים והנחות'!$F$22),0),'נתונים והנחות'!$G$48*0.1*'נתונים והנחות'!$F$22,0),0) | Z87: =IF(ISNUMBER('נתונים והנחות'!$G$48),IF(20<=ROUND(1/(0.1*'נתונים והנחות'!$F$22),0),'נתונים והנחות'!$G$48*0.1*'נתונים והנחות'!$F$22,0),0)
B88: מגן מס מואץ — צ'ילרים | C88: ₪ | D88: חישוב | E88: =פחת מואץ × שיעור מס | F88: 0 | G88: =G87*'נתונים והנחות'!$F$10 | H88: =H87*'נתונים והנחות'!$F$10 | I88: =I87*'נתונים והנחות'!$F$10 | J88: =J87*'נתונים והנחות'!$F$10 | K88: =K87*'נתונים והנחות'!$F$10 | L88: =L87*'נתונים והנחות'!$F$10 | M88: =M87*'נתונים והנחות'!$F$10 | N88: =N87*'נתונים והנחות'!$F$10 | ... Z88: =Z87*'נתונים והנחות'!$F$10
B90: ג. ניתוח תזרים מזומנים — שלושה תרחישים
B91: פרמטר | C91: יחידות | D91: מקור | E91: הערות | F91: שנה 0 (השקעה) | G91: שנה 1 | H91: שנה 2 | I91: שנה 3 | J91: שנה 4 | K91: שנה 5 | L91: שנה 6 | M91: שנה 7 | N91: שנה 8 | O91: שנה 9 | P91: שנה 10 | Q91: שנה 11 | R91: שנה 12 | S91: שנה 13 | T91: שנה 14 | U91: שנה 15 | V91: שנה 16 | W91: שנה 17 | X91: שנה 18 | Y91: שנה 19 | Z91: שנה 20
B92: תרחיש A — רכישת מערכת קירור קונבנציונלית (ציוד קיים / לא יעיל)
B93: השקעה ראשונית | C93: ₪ | D93: חישוב | F93: =IF(ISNUMBER('נתונים והנחות'!$G$47),-'נתונים והנחות'!$G$47,"PENDING")
B94: OPEX אנרגיה | C94: ₪ | D94: חישוב | F94: 0 | G94: =IF(ISNUMBER('נתונים והנחות'!$G$55),-'נתונים והנחות'!$G$55,0) | H94: =IF(ISNUMBER('נתונים והנחות'!$G$55),-'נתונים והנחות'!$G$55,0) | I94: =IF(ISNUMBER('נתונים והנחות'!$G$55),-'נתונים והנחות'!$G$55,0) | J94: =IF(ISNUMBER('נתונים והנחות'!$G$55),-'נתונים והנחות'!$G$55,0) | K94: =IF(ISNUMBER('נתונים והנחות'!$G$55),-'נתונים והנחות'!$G$55,0) | L94: =IF(ISNUMBER('נתונים והנחות'!$G$55),-'נתונים והנחות'!$G$55,0) | M94: =IF(ISNUMBER('נתונים והנחות'!$G$55),-'נתונים והנחות'!$G$55,0) | N94: =IF(ISNUMBER('נתונים והנחות'!$G$55),-'נתונים והנחות'!$G$55,0) | ... U94: =IF(ISNUMBER('נתונים והנחות'!$G$55),-'נתונים והנחות'!$G$55,0) | V94: =0 | W94: =0 | X94: =0 | Y94: =0 | Z94: =0
B95: OPEX אחר (תחזוקה וכו') | C95: ₪ | D95: חישוב | F95: 0 | G95: =IF(ISNUMBER('נתונים והנחות'!$G$53),-'נתונים והנחות'!$G$53,0) | H95: =IF(ISNUMBER('נתונים והנחות'!$G$53),-'נתונים והנחות'!$G$53,0) | I95: =IF(ISNUMBER('נתונים והנחות'!$G$53),-'נתונים והנחות'!$G$53,0) | J95: =IF(ISNUMBER('נתונים והנחות'!$G$53),-'נתונים והנחות'!$G$53,0) | K95: =IF(ISNUMBER('נתונים והנחות'!$G$53),-'נתונים והנחות'!$G$53,0) | L95: =IF(ISNUMBER('נתונים והנחות'!$G$53),-'נתונים והנחות'!$G$53,0) | M95: =IF(ISNUMBER('נתונים והנחות'!$G$53),-'נתונים והנחות'!$G$53,0) | N95: =IF(ISNUMBER('נתונים והנחות'!$G$53),-'נתונים והנחות'!$G$53,0) | ... U95: =IF(ISNUMBER('נתונים והנחות'!$G$53),-'נתונים והנחות'!$G$53,0) | V95: =0 | W95: =0 | X95: =0 | Y95: =0 | Z95: =0
B96: תזרים נקי — תרחיש A | C96: ₪ | D96: חישוב | F96: =F93 | G96: =G94+G95+G84 | H96: =H94+H95+H84 | I96: =I94+I95+I84 | J96: =J94+J95+J84 | K96: =K94+K95+K84 | L96: =L94+L95+L84 | M96: =M94+M95+M84 | N96: =N94+N95+N84 | ... Z96: =Z94+Z95+Z84
B97: תזרים מהוון — תרחיש A | C97: ₪ | D97: חישוב | F97: =F96 | G97: =G96/(1+'נתונים והנחות'!$F$11)^1 | H97: =H96/(1+'נתונים והנחות'!$F$11)^2 | I97: =I96/(1+'נתונים והנחות'!$F$11)^3 | J97: =J96/(1+'נתונים והנחות'!$F$11)^4 | K97: =K96/(1+'נתונים והנחות'!$F$11)^5 | L97: =L96/(1+'נתונים והנחות'!$F$11)^6 | M97: =M96/(1+'נתונים והנחות'!$F$11)^7 | N97: =N96/(1+'נתונים והנחות'!$F$11)^8 | O97: =O96/(1+'נתונים והנחות'!$F$11)^9 | P97: =P96/(1+'נתונים והנחות'!$F$11)^10 | Q97: =Q96/(1+'נתונים והנחות'!$F$11)^11 | R97: =R96/(1+'נתונים והנחות'!$F$11)^12 | S97: =S96/(1+'נתונים והנחות'!$F$11)^13 | T97: =T96/(1+'נתונים והנחות'!$F$11)^14 | U97: =U96/(1+'נתונים והנחות'!$F$11)^15 | V97: =V96/(1+'נתונים והנחות'!$F$11)^16 | W97: =W96/(1+'נתונים והנחות'!$F$11)^17 | X97: =X96/(1+'נתונים והנחות'!$F$11)^18 | Y97: =Y96/(1+'נתונים והנחות'!$F$11)^19 | Z97: =Z96/(1+'נתונים והנחות'!$F$11)^20
B98: NPV מצטבר — תרחיש A | C98: ₪ | D98: חישוב | F98: =F97 | G98: =F98+G97 | H98: =G98+H97 | I98: =H98+I97 | J98: =I98+J97 | K98: =J98+K97 | L98: =K98+L97 | M98: =L98+M97 | N98: =M98+N97 | ... Z98: =Y98+Z97
B100: תרחיש B — רכישת צ'ילרים | פחת סטנדרטי (ללא תמריץ)
B101: השקעה ראשונית | C101: ₪ | D101: חישוב | F101: =IF(ISNUMBER('נתונים והנחות'!$G$48),-'נתונים והנחות'!$G$48,"PENDING")
B102: OPEX אנרגיה (עם שחיקה שנתית) | C102: ₪ | D102: חישוב | F102: 0 | G102: =IF(ISNUMBER('נתונים והנחות'!$G$56),-'נתונים והנחות'!$G$56*(1-'נתונים והנחות'!$G$52)^0,0) | H102: =IF(ISNUMBER('נתונים והנחות'!$G$56),-'נתונים והנחות'!$G$56*(1-'נתונים והנחות'!$G$52)^1,0) | I102: =IF(ISNUMBER('נתונים והנחות'!$G$56),-'נתונים והנחות'!$G$56*(1-'נתונים והנחות'!$G$52)^2,0) | J102: =IF(ISNUMBER('נתונים והנחות'!$G$56),-'נתונים והנחות'!$G$56*(1-'נתונים והנחות'!$G$52)^3,0) | K102: =IF(ISNUMBER('נתונים והנחות'!$G$56),-'נתונים והנחות'!$G$56*(1-'נתונים והנחות'!$G$52)^4,0) | L102: =IF(ISNUMBER('נתונים והנחות'!$G$56),-'נתונים והנחות'!$G$56*(1-'נתונים והנחות'!$G$52)^5,0) | M102: =IF(ISNUMBER('נתונים והנחות'!$G$56),-'נתונים והנחות'!$G$56*(1-'נתונים והנחות'!$G$52)^6,0) | N102: =IF(ISNUMBER('נתונים והנחות'!$G$56),-'נתונים והנחות'!$G$56*(1-'נתונים והנחות'!$G$52)^7,0) | O102: =IF(ISNUMBER('נתונים והנחות'!$G$56),-'נתונים והנחות'!$G$56*(1-'נתונים והנחות'!$G$52)^8,0) | P102: =IF(ISNUMBER('נתונים והנחות'!$G$56),-'נתונים והנחות'!$G$56*(1-'נתונים והנחות'!$G$52)^9,0) | Q102: =IF(ISNUMBER('נתונים והנחות'!$G$56),-'נתונים והנחות'!$G$56*(1-'נתונים והנחות'!$G$52)^10,0) | R102: =IF(ISNUMBER('נתונים והנחות'!$G$56),-'נתונים והנחות'!$G$56*(1-'נתונים והנחות'!$G$52)^11,0) | S102: =IF(ISNUMBER('נתונים והנחות'!$G$56),-'נתונים והנחות'!$G$56*(1-'נתונים והנחות'!$G$52)^12,0) | T102: =IF(ISNUMBER('נתונים והנחות'!$G$56),-'נתונים והנחות'!$G$56*(1-'נתונים והנחות'!$G$52)^13,0) | U102: =IF(ISNUMBER('נתונים והנחות'!$G$56),-'נתונים והנחות'!$G$56*(1-'נתונים והנחות'!$G$52)^14,0) | V102: =IF(ISNUMBER('נתונים והנחות'!$G$56),-'נתונים והנחות'!$G$56*(1-'נתונים והנחות'!$G$52)^15,0) | W102: =IF(ISNUMBER('נתונים והנחות'!$G$56),-'נתונים והנחות'!$G$56*(1-'נתונים והנחות'!$G$52)^16,0) | X102: =0 | Y102: =0 | Z102: =0
B103: OPEX אחר (תחזוקה וכו') | C103: ₪ | D103: חישוב | F103: 0 | G103: =IF(ISNUMBER('נתונים והנחות'!$G$54),-'נתונים והנחות'!$G$54,0) | H103: =IF(ISNUMBER('נתונים והנחות'!$G$54),-'נתונים והנחות'!$G$54,0) | I103: =IF(ISNUMBER('נתונים והנחות'!$G$54),-'נתונים והנחות'!$G$54,0) | J103: =IF(ISNUMBER('נתונים והנחות'!$G$54),-'נתונים והנחות'!$G$54,0) | K103: =IF(ISNUMBER('נתונים והנחות'!$G$54),-'נתונים והנחות'!$G$54,0) | L103: =IF(ISNUMBER('נתונים והנחות'!$G$54),-'נתונים והנחות'!$G$54,0) | M103: =IF(ISNUMBER('נתונים והנחות'!$G$54),-'נתונים והנחות'!$G$54,0) | N103: =IF(ISNUMBER('נתונים והנחות'!$G$54),-'נתונים והנחות'!$G$54,0) | ... W103: =IF(ISNUMBER('נתונים והנחות'!$G$54),-'נתונים והנחות'!$G$54,0) | X103: =0 | Y103: =0 | Z103: =0
B104: תזרים נקי — תרחיש B | C104: ₪ | D104: חישוב | F104: =F101 | G104: =G102+G103+G86 | H104: =H102+H103+H86 | I104: =I102+I103+I86 | J104: =J102+J103+J86 | K104: =K102+K103+K86 | L104: =L102+L103+L86 | M104: =M102+M103+M86 | N104: =N102+N103+N86 | ... Z104: =Z102+Z103+Z86
B105: תזרים מהוון — תרחיש B | C105: ₪ | D105: חישוב | F105: =F104 | G105: =G104/(1+'נתונים והנחות'!$F$11)^1 | H105: =H104/(1+'נתונים והנחות'!$F$11)^2 | I105: =I104/(1+'נתונים והנחות'!$F$11)^3 | J105: =J104/(1+'נתונים והנחות'!$F$11)^4 | K105: =K104/(1+'נתונים והנחות'!$F$11)^5 | L105: =L104/(1+'נתונים והנחות'!$F$11)^6 | M105: =M104/(1+'נתונים והנחות'!$F$11)^7 | N105: =N104/(1+'נתונים והנחות'!$F$11)^8 | O105: =O104/(1+'נתונים והנחות'!$F$11)^9 | P105: =P104/(1+'נתונים והנחות'!$F$11)^10 | Q105: =Q104/(1+'נתונים והנחות'!$F$11)^11 | R105: =R104/(1+'נתונים והנחות'!$F$11)^12 | S105: =S104/(1+'נתונים והנחות'!$F$11)^13 | T105: =T104/(1+'נתונים והנחות'!$F$11)^14 | U105: =U104/(1+'נתונים והנחות'!$F$11)^15 | V105: =V104/(1+'נתונים והנחות'!$F$11)^16 | W105: =W104/(1+'נתונים והנחות'!$F$11)^17 | X105: =X104/(1+'נתונים והנחות'!$F$11)^18 | Y105: =Y104/(1+'נתונים והנחות'!$F$11)^19 | Z105: =Z104/(1+'נתונים והנחות'!$F$11)^20
B106: NPV מצטבר — תרחיש B | C106: ₪ | D106: חישוב | F106: =F105 | G106: =F106+G105 | H106: =G106+H105 | I106: =H106+I105 | J106: =I106+J105 | K106: =J106+K105 | L106: =K106+L105 | M106: =L106+M105 | N106: =M106+N105 | ... Z106: =Y106+Z105
B108: תרחיש C — רכישת צ'ילרים | פחת מואץ (עם תמריץ)
B109: * OPEX זהה לתרחיש B — ההבדל הוא מגן המס המואץ בלבד
B110: תזרים נקי — תרחיש C | C110: ₪ | D110: חישוב | F110: =F101 | G110: =G102+G103+G88 | H110: =H102+H103+H88 | I110: =I102+I103+I88 | J110: =J102+J103+J88 | K110: =K102+K103+K88 | L110: =L102+L103+L88 | M110: =M102+M103+M88 | N110: =N102+N103+N88 | ... Z110: =Z102+Z103+Z88
B111: תזרים מהוון — תרחיש C | C111: ₪ | D111: חישוב | F111: =F110 | G111: =G110/(1+'נתונים והנחות'!$F$11)^1 | H111: =H110/(1+'נתונים והנחות'!$F$11)^2 | I111: =I110/(1+'נתונים והנחות'!$F$11)^3 | J111: =J110/(1+'נתונים והנחות'!$F$11)^4 | K111: =K110/(1+'נתונים והנחות'!$F$11)^5 | L111: =L110/(1+'נתונים והנחות'!$F$11)^6 | M111: =M110/(1+'נתונים והנחות'!$F$11)^7 | N111: =N110/(1+'נתונים והנחות'!$F$11)^8 | O111: =O110/(1+'נתונים והנחות'!$F$11)^9 | P111: =P110/(1+'נתונים והנחות'!$F$11)^10 | Q111: =Q110/(1+'נתונים והנחות'!$F$11)^11 | R111: =R110/(1+'נתונים והנחות'!$F$11)^12 | S111: =S110/(1+'נתונים והנחות'!$F$11)^13 | T111: =T110/(1+'נתונים והנחות'!$F$11)^14 | U111: =U110/(1+'נתונים והנחות'!$F$11)^15 | V111: =V110/(1+'נתונים והנחות'!$F$11)^16 | W111: =W110/(1+'נתונים והנחות'!$F$11)^17 | X111: =X110/(1+'נתונים והנחות'!$F$11)^18 | Y111: =Y110/(1+'נתונים והנחות'!$F$11)^19 | Z111: =Z110/(1+'נתונים והנחות'!$F$11)^20
B112: NPV מצטבר — תרחיש C | C112: ₪ | D112: חישוב | F112: =F111 | G112: =F112+G111 | H112: =G112+H111 | I112: =H112+I111 | J112: =I112+J111 | K112: =J112+K111 | L112: =K112+L111 | M112: =L112+M111 | N112: =M112+N111 | ... Z112: =Y112+Z111
B114: ד. תוצאות
B115: NPV — תרחיש A (מערכת קירור קונבנציונלית) | C115: ש"ח | F115: =SUM(F97:Z97)
B116: NPV — תרחיש B (צ'ילרים, ללא תמריץ) | C116: ש"ח | F116: =SUM(F105:Z105)
B117: NPV — תרחיש C (צ'ילרים, עם תמריץ) | C117: ש"ח | F117: =SUM(F111:Z111)
B119: NPV מצטבר — הצדקת השדרוג (B−A) | C119: ש"ח | F119: =F116-F115
B120: ערך התמריץ — תועלת הפחת המואץ (C−B) | C120: ש"ח | F120: =F117-F116
...
