Workbook

Sheet Summary
A1: Travel Budget -- September Europe Trip
A2: Norway → London → Scotland → Ireland → Portugal, Sept 8 - ~Dec 8 2026 (excludes flights)
A3: Last updated: | B3: 46215
A5: FUNDING
A6: Confirmed baseline (grant + savings) | B6: ='Funding Sources'!D7 -> 18000
A7: + Parental help (buffer, not fixed) | B7: ='Funding Sources'!D4 -> 0
A8: + Work exchange savings (estimate) | B8: ='Funding Sources'!D5 -> 1500
A9: Total available incl. buffers | B9: =B6+B7+B8 -> 19500
A11: BUDGETED COST (plan, before the trip)
A12: Budgeted -- Low (frugal, disciplined) | B12: ='Budget Plan'!K10 -> 18653.85
A13: Budgeted -- High (moderate comfort) | B13: ='Budget Plan'!L10 -> 29345.75
A15: SURPLUS / (SHORTFALL)
A16: vs. Confirmed baseline -- Low | B16: =B6-B12 -> -653.85
A17: vs. Confirmed baseline -- High | B17: =B6-B13 -> -11345.75
A18: vs. Total incl. buffers -- Low | B18: =B9-B12 -> 846.15
A19: vs. Total incl. buffers -- High | B19: =B9-B13 -> -9845.75
A21: ACTUAL SPENDING (live, updates as you fill in the Expense Log)
A22: Actual spent so far | B22: =SUM('Expense Log'!H:H) -> 0
A23: Remaining vs. confirmed baseline | B23: =B6-B22 -> 18000
A24: Remaining vs. total incl. buffers | B24: =B9-B22 -> 19500
A26: SPENDING BY CATEGORY (ILS, live)
A27: Accommodation | B27: =SUMIF('Expense Log'!C:C,A27,'Expense Log'!H:H) -> 0
A28: Food | B28: =SUMIF('Expense Log'!C:C,A28,'Expense Log'!H:H) -> 0
A29: Transport | B29: =SUMIF('Expense Log'!C:C,A29,'Expense Log'!H:H) -> 0
A30: Activities | B30: =SUMIF('Expense Log'!C:C,A30,'Expense Log'!H:H) -> 0
A31: Gear/Insurance | B31: =SUMIF('Expense Log'!C:C,A31,'Expense Log'!H:H) -> 0
A32: Other | B32: =SUMIF('Expense Log'!C:C,A32,'Expense Log'!H:H) -> 0
A34: How to use this workbook
A35: - Rates tab: update the exchange rates before you leave and periodically while traveling -- everything else recalculates automatically.
A36: - Funding Sources tab: adjust Parental Help and Work Exchange Savings as those firm up -- they're deliberately excluded from the confirmed baseline.
A37: - Budget Plan tab: the Low/High per-leg estimates are planning assumptions, not fixed rules -- edit freely as you learn real prices.
A38: - Expense Log tab: log every real expense here while traveling (pick Leg/Category from the dropdowns, enter the local-currency amount) -- this Summary tab updates live.

Sheet Rates
A1: Currency | B1: Rate to ILS (1 unit = ₪) | C1: Notes
A2: EUR | B2: 3.43 | C2: EUR/ILS ~0.2916 ILS/EUR as of 2026-07-12 -- update before/during trip
A3: GBP | B3: 4.02 | C3: GBP/ILS ~0.249 ILS/GBP as of 2026-07-12
A4: NOK | B4: 0.31 | C4: NOK/ILS ~0.3107 as of 2026-07-12
A5: ILS | B5: 1 | C5: Base currency

Sheet Funding Sources
A1: Source | B1: Amount | C1: Currency | D1: ILS Equivalent | E1: Counted in Baseline? | F1: Notes
A2: Military service grant | B2: 15000 | C2: ILS | D2: =IF(C2="ILS",B2,B2*INDEX(Rates!$B$2:$B$5,MATCH(C2,Rates!$A$2:$A$5,0))) -> 15000 | E2: Yes | F2: Confirmed
A3: Savings (last 2 months) | B3: 3000 | C3: ILS | D3: =IF(C3="ILS",B3,B3*INDEX(Rates!$B$2:$B$5,MATCH(C3,Rates!$A$2:$A$5,0))) -> 3000 | E3: Yes | F3: Confirmed
A4: Parental help (backup) | B4: 0 | C4: ILS | D4: =IF(C4="ILS",B4,B4*INDEX(Rates!$B$2:$B$5,MATCH(C4,Rates!$A$2:$A$5,0))) -> 0 | E4: No | F4: Not a fixed amount -- covers travel costs + small things as needed. Treat as a safety buffer, not part of the baseline math. Update if a number firms up.
A5: Work/volunteer exchange (estimated savings) | B5: 1500 | C5: ILS | D5: =IF(C5="ILS",B5,B5*INDEX(Rates!$B$2:$B$5,MATCH(C5,Rates!$A$2:$A$5,0))) -> 1500 | E5: No | F5: Estimate only -- assumes ~2-3 weeks of room+board covered somewhere on the trip. Adjust once an exchange is actually arranged.
A7: TOTAL CONFIRMED BASELINE (ILS) | D7: =D2+D3 -> 18000
A8: TOTAL INCLUDING BUFFERS (ILS) | D8: =D2+D3+D4+D5 -> 19500

Sheet Budget Plan
A1: Leg | B1: Start Date | C1: End Date | D1: Days | E1: Local Currency | F1: Daily Budget - Low | G1: Daily Budget - High | H1: Total - Low (Local) | I1: Total - High (Local) | J1: Rate to ILS | K1: Total - Low (ILS) | L1: Total - High (ILS) | M1: Notes
A2: Norway | B2: 46273 | C2: 46300 | D2: =C2-B2+1 -> 28 | E2: NOK | F2: 550 | G2: 1000 | H2: =D2*F2 -> 15400 | I2: =D2*G2 -> 28000 | J2: =INDEX(Rates!$B$2:$B$5,MATCH(E2,Rates!$A$2:$A$5,0)) -> 0.31 | K2: =H2*J2 -> 4774 | L2: =I2*J2 -> 8680 | M2: Frugal-high range assumes mixed wild camping (allemannsretten, free) / DNT huts / occasional hostel, self-catering most meals. Most expensive leg per day -- the real budget risk.
A3: London | B3: 46300 | C3: 46314 | D3: =C3-B3+1 -> 15 | E3: GBP | F3: 40 | G3: 60 | H3: =D3*F3 -> 600 | I3: =D3*G3 -> 900 | J3: =INDEX(Rates!$B$2:$B$5,MATCH(E3,Rates!$A$2:$A$5,0)) -> 4.02 | K3: =H3*J3 -> 2412 | L3: =I3*J3 -> 3618 | M3: Hostel dorm + self-catering some meals + advance transport tickets, per UK backpacker averages.
A4: Scotland | B4: 46314 | C4: 46328 | D4: =C4-B4+1 -> 15 | E4: GBP | F4: 35 | G4: 50 | H4: =D4*F4 -> 525 | I4: =D4*G4 -> 750 | J4: =INDEX(Rates!$B$2:$B$5,MATCH(E4,Rates!$A$2:$A$5,0)) -> 4.02 | K4: =H4*J4 -> 2110.5 | L4: =I4*J4 -> 3015 | M4: Similar to London, slightly cheaper outside the capital.
A5: Ireland | B5: 46328 | C5: 46342 | D5: =C5-B5+1 -> 15 | E5: EUR | F5: 55 | G5: 75 | H5: =D5*F5 -> 825 | I5: =D5*G5 -> 1125 | J5: =INDEX(Rates!$B$2:$B$5,MATCH(E5,Rates!$A$2:$A$5,0)) -> 3.43 | K5: =H5*J5 -> 2829.75 | L5: =I5*J5 -> 3858.75 | M5: Avoid Dublin hostel premium where possible -- prices spike hard there.
A6: Portugal | B6: 46342 | C6: 46365 | D6: =C6-B6+1 -> 24 | E6: EUR | F6: 55 | G6: 75 | H6: =D6*F6 -> 1320 | I6: =D6*G6 -> 1800 | J6: =INDEX(Rates!$B$2:$B$5,MATCH(E6,Rates!$A$2:$A$5,0)) -> 3.43 | K6: =H6*J6 -> 4527.6 | L6: =I6*J6 -> 6174 | M6: Cheapest of the non-Norway legs; cheaper still outside Lisbon/Porto.
A7: Pre-Trip Gear & Insurance | D7: - | E7: ILS | H7: 1500 | I7: 2500 | J7: =INDEX(Rates!$B$2:$B$5,MATCH(E7,Rates!$A$2:$A$5,0)) -> 1 | K7: =H7*J7 -> 1500 | L7: =I7*J7 -> 2500 | M7: Travel insurance, hiking/camping gear, DNT membership, etc. Edit directly -- not day-rate based.
A8: Emergency Buffer | D8: - | E8: ILS | H8: 500 | I8: 1500 | J8: =INDEX(Rates!$B$2:$B$5,MATCH(E8,Rates!$A$2:$A$5,0)) -> 1 | K8: =H8*J8 -> 500 | L8: =I8*J8 -> 1500 | M8: Unplanned costs: missed connections, gear replacement, illness. Edit directly.
A10: TOTAL | K10: =SUM(K2:K8) -> 18653.85 | L10: =SUM(L2:L8) -> 29345.75

Sheet Expense Log
A1: Date | B1: Leg / Location | C1: Category | D1: Description | E1: Currency | F1: Amount (Local) | G1: Rate to ILS | H1: Amount (ILS) | I1: Running Total (ILS) | J1: Notes
G2: =IF(E2="","",INDEX(Rates!$B$2:$B$5,MATCH(E2,Rates!$A$2:$A$5,0))) | H2: =IF(F2="","",F2*G2) | I2: =IF(H2="","",SUM($H$2:H2))
G3: =IF(E3="","",INDEX(Rates!$B$2:$B$5,MATCH(E3,Rates!$A$2:$A$5,0))) | H3: =IF(F3="","",F3*G3) | I3: =IF(H3="","",SUM($H$2:H3))
G4: =IF(E4="","",INDEX(Rates!$B$2:$B$5,MATCH(E4,Rates!$A$2:$A$5,0))) | H4: =IF(F4="","",F4*G4) | I4: =IF(H4="","",SUM($H$2:H4))
G5: =IF(E5="","",INDEX(Rates!$B$2:$B$5,MATCH(E5,Rates!$A$2:$A$5,0))) | H5: =IF(F5="","",F5*G5) | I5: =IF(H5="","",SUM($H$2:H5))
G6: =IF(E6="","",INDEX(Rates!$B$2:$B$5,MATCH(E6,Rates!$A$2:$A$5,0))) | H6: =IF(F6="","",F6*G6) | I6: =IF(H6="","",SUM($H$2:H6))
G7: =IF(E7="","",INDEX(Rates!$B$2:$B$5,MATCH(E7,Rates!$A$2:$A$5,0))) | H7: =IF(F7="","",F7*G7) | I7: =IF(H7="","",SUM($H$2:H7))
G8: =IF(E8="","",INDEX(Rates!$B$2:$B$5,MATCH(E8,Rates!$A$2:$A$5,0))) | H8: =IF(F8="","",F8*G8) | I8: =IF(H8="","",SUM($H$2:H8))
G9: =IF(E9="","",INDEX(Rates!$B$2:$B$5,MATCH(E9,Rates!$A$2:$A$5,0))) | H9: =IF(F9="","",F9*G9) | I9: =IF(H9="","",SUM($H$2:H9))
G10: =IF(E10="","",INDEX(Rates!$B$2:$B$5,MATCH(E10,Rates!$A$2:$A$5,0))) | H10: =IF(F10="","",F10*G10) | I10: =IF(H10="","",SUM($H$2:H10))
G11: =IF(E11="","",INDEX(Rates!$B$2:$B$5,MATCH(E11,Rates!$A$2:$A$5,0))) | H11: =IF(F11="","",F11*G11) | I11: =IF(H11="","",SUM($H$2:H11))
G12: =IF(E12="","",INDEX(Rates!$B$2:$B$5,MATCH(E12,Rates!$A$2:$A$5,0))) | H12: =IF(F12="","",F12*G12) | I12: =IF(H12="","",SUM($H$2:H12))
G13: =IF(E13="","",INDEX(Rates!$B$2:$B$5,MATCH(E13,Rates!$A$2:$A$5,0))) | H13: =IF(F13="","",F13*G13) | I13: =IF(H13="","",SUM($H$2:H13))
... G251: =IF(E251="","",INDEX(Rates!$B$2:$B$5,MATCH(E251,Rates!$A$2:$A$5,0))) | H251: =IF(F251="","",F251*G251) | I251: =IF(H251="","",SUM($H$2:H251))
